pyflutterflow/__init__.py
pyflutterflow/auth.py
pyflutterflow/base_service.py
pyflutterflow/constants.py
pyflutterflow/dashboard/README.md
pyflutterflow/dashboard/dist/assets/comfortaa-cyrillic-ext-wght-normal-CXKR5IiB.woff2
pyflutterflow/dashboard/dist/assets/comfortaa-cyrillic-wght-normal-vbOIvbbL.woff2
pyflutterflow/dashboard/dist/assets/comfortaa-greek-wght-normal-BaxD78s7.woff2
pyflutterflow/dashboard/dist/assets/comfortaa-latin-ext-wght-normal-C2476TZz.woff2
pyflutterflow/dashboard/dist/assets/comfortaa-latin-wght-normal-Bn-F1k5z.woff2
pyflutterflow/dashboard/dist/assets/comfortaa-vietnamese-wght-normal-DURqo7ac.woff2
pyflutterflow/dashboard/dist/assets/fa-brands-400-Dur5g48u.ttf
pyflutterflow/dashboard/dist/assets/fa-brands-400-O7nZalfM.woff2
pyflutterflow/dashboard/dist/assets/fa-regular-400-Bf3rG5Nx.ttf
pyflutterflow/dashboard/dist/assets/fa-regular-400-DgEfZSYE.woff2
pyflutterflow/dashboard/dist/assets/fa-solid-900-BV3CbEM2.ttf
pyflutterflow/dashboard/dist/assets/fa-solid-900-DOQJEhcS.woff2
pyflutterflow/dashboard/dist/assets/fa-v4compatibility-B9MWI-E6.ttf
pyflutterflow/dashboard/dist/assets/fa-v4compatibility-BX8XWJtE.woff2
pyflutterflow/dashboard/dist/assets/index-BWjNLLto.js
pyflutterflow/dashboard/dist/assets/index-aeoF4eu7.css
pyflutterflow/dashboard/dist/assets/inter-cyrillic-ext-wght-normal-B2xhLi22.woff2
pyflutterflow/dashboard/dist/assets/inter-cyrillic-wght-normal-CMZtQduZ.woff2
pyflutterflow/dashboard/dist/assets/inter-greek-ext-wght-normal-CGAr0uHJ.woff2
pyflutterflow/dashboard/dist/assets/inter-greek-wght-normal-CaVNZxsx.woff2
pyflutterflow/dashboard/dist/assets/inter-latin-ext-wght-normal-CFHvXkgd.woff2
pyflutterflow/dashboard/dist/assets/inter-latin-wght-normal-C2S99t-D.woff2
pyflutterflow/dashboard/dist/assets/inter-vietnamese-wght-normal-CBcvBZtf.woff2
pyflutterflow/dashboard/dist/assets/logo-ByLmkyx8.png
pyflutterflow/dashboard/dist/assets/open-sans-cyrillic-ext-wght-normal-f7eF65bT.woff2
pyflutterflow-0.5.1.dist-info/METADATA
pyflutterflow-0.5.1.dist-info/WHEEL
pyflutterflow-0.5.1.dist-info/entry_points.txt
pyflutterflow-0.5.1.dist-info/RECORD
